README.md
setup.cfg
setup.py
pypbi/__init__.py
pypbi/classes.py
pypbi/constants.py
pypbi/core.py
pypbi.egg-info/PKG-INFO
pypbi.egg-info/SOURCES.txt
pypbi.egg-info/dependency_links.txt
pypbi.egg-info/requires.txt
pypbi.egg-info/top_level.txt