Metadata-Version: 1.1
Name: pypbi
Version: 0.0.3
Summary: An Unofficial Python wrapper around PowerBI REST API
Home-page: https://github.com/vykhand/pypbi
Author: Andrey Vykhodtsev
Author-email: vykhand@outlook.com
License: UNKNOWN
Download-URL: https://github.com/vykhand/pypbi/archive/0.0.3.tar.gz
Keywords: powerbi
Platform: UNKNOWN
